README.md
setup.py
ppi/__init__.py
ppi/__main__.py
ppi/commands.py
ppi/console.py
ppi/core.py
ppi/local_cmds.py
ppi/version.py
ppi.egg-info/PKG-INFO
ppi.egg-info/SOURCES.txt
ppi.egg-info/dependency_links.txt
ppi.egg-info/entry_points.txt
ppi.egg-info/requires.txt
ppi.egg-info/top_level.txt
tests/demo/__init__.py
tests/demo/setup.py
tests/demo/version.py