Metadata-Version: 1.2
Name: ppi
Version: 0.0.4
Summary: A command line tool help you to publish your python project on github and pypi
Home-page: https://github.com/jeremaihloo/ppi
Author: jeremaihloo
Author-email: jeremaihloo1024@gmail.com
License: UNKNOWN
Project-URL: Bug Reports, https://github.com/jeremaihloo/ppi/issues
Project-URL: Source, https://github.com/jeremaihloo/ppi
Platform: UNKNOWN
